timezone_utils/__init__.py
timezone_utils/choices.py
timezone_utils/fields.py
timezone_utils/forms.py
django_timezone_utils-0.15.0.dist-info/LICENSE
django_timezone_utils-0.15.0.dist-info/METADATA
django_timezone_utils-0.15.0.dist-info/WHEEL
django_timezone_utils-0.15.0.dist-info/top_level.txt
django_timezone_utils-0.15.0.dist-info/RECORD
